README.md
setup.py
ArtisanKit/__init__.py
ArtisanKit/iostream.py
ArtisanKit/plotting.py
ArtisanKit/statistics.py
ArtisanKit.egg-info/PKG-INFO
ArtisanKit.egg-info/SOURCES.txt
ArtisanKit.egg-info/dependency_links.txt
ArtisanKit.egg-info/top_level.txt