Metadata-Version: 2.1
Name: ArtisanKit
Version: 0.0.3
Summary: A Productivity Toolkit for Craftsman/woman Doing Research in Computational Chemistry, Machine Learning, and Beyond.
Home-page: https://github.com/xiangsunlab/ArtisanKit
Author: dominikusbrian
Author-email: dominikusbrian@nyu.com
License: UNKNOWN
Platform: UNKNOWN
Classifier: Programming Language :: Python :: 3
Classifier: License :: OSI Approved :: GNU Lesser General Public License v3 (LGPLv3)
Classifier: Operating System :: OS Independent
Requires-Python: >=3.8
